SX127x/LoRa.py
SX127x/LoRaArgumentParser.py
SX127x/__init__.py
SX127x/board_config.py
SX127x/constants.py
pyLoRa-0.3.0.dist-info/LICENSE
pyLoRa-0.3.0.dist-info/METADATA
pyLoRa-0.3.0.dist-info/WHEEL
pyLoRa-0.3.0.dist-info/top_level.txt
pyLoRa-0.3.0.dist-info/RECORD
