Metadata-Version: 2.1
Name: pyLoRa
Version: 0.3.0
Summary: (LoRa communication 868MHz VERSION) This is a python interface to the Semtech SX1276/7/8/9 long range, low power transceiver family.
Home-page: https://github.com/rpsreal/pySX127x
Author: Rui Silva
Author-email: ruisilva.real@sapo.pt
License: UNKNOWN
Platform: UNKNOWN
Classifier: Programming Language :: Python :: 3
Classifier: Natural Language :: Portuguese
Classifier: Topic :: Scientific/Engineering :: Interface Engine/Protocol Translator
Classifier: License :: OSI Approved :: GNU General Public License v3 (GPLv3)
Classifier: Operating System :: POSIX :: Linux
